Metadata-Version: 1.2
Name: dbmgt
Version: 1.1
Summary: mysql management package
Home-page: http://blog.swcloud.top
Author: sunway
Author-email: sw1022@gmail.com
License: MIT License
Keywords: bee,egg
Platform: any
Requires-Python: >=3.5, <=3.8
